fangraphs/__init__.py
fangraphs/exceptions.py
fangraphs/leaders.py
fangraphs/utilities.py
fangraphs/selectors/__init__.py
fangraphs/selectors/leaders_sel.py
fangraphs/tests/__init__.py
fangraphs/tests/test_leaders.py
fangraphs-1.0.1.dist-info/AUTHORS
fangraphs-1.0.1.dist-info/LICENSE
fangraphs-1.0.1.dist-info/METADATA
fangraphs-1.0.1.dist-info/WHEEL
fangraphs-1.0.1.dist-info/pbr.json
fangraphs-1.0.1.dist-info/top_level.txt
fangraphs-1.0.1.dist-info/RECORD
