Metadata-Version: 2.1
Name: fangraphs
Version: 1.0.1
Summary: UNKNOWN
Home-page: http://github.com/JLpython-py/FanGraphs-Export
Author: Jacob Lee
Author-email: JLpython@outlook.com
License: MIT
Platform: UNKNOWN
Classifier: Development Status :: 5 - Production/Stable
Classifier: Intended Audience :: Developers
Classifier: License :: OSI Approved :: MIT License
Classifier: Operating System :: OS Independent
Classifier: Programming Language :: Python
Classifier: Programming Language :: Python :: 3.6
Classifier: Programming Language :: Python :: 3.7
Classifier: Programming Language :: Python :: 3.8
Classifier: Programming Language :: Python :: 3.9
Requires-Dist: atomicwrites (==1.4.0)
Requires-Dist: attrs (==20.3.0)
Requires-Dist: beautifulsoup4 (==4.9.3)
Requires-Dist: certifi (==2020.12.5)
Requires-Dist: chardet (==4.0.0)
Requires-Dist: colorama (==0.4.4)
Requires-Dist: greenlet (==1.0.0)
Requires-Dist: idna (==2.10)
Requires-Dist: iniconfig (==1.1.1)
Requires-Dist: lxml (==4.6.3)
Requires-Dist: packaging (==20.9)
Requires-Dist: playwright (==1.10.0)
Requires-Dist: pluggy (==0.13.1)
Requires-Dist: py (==1.10.0)
Requires-Dist: pyee (==8.1.0)
Requires-Dist: pyparsing (==2.4.7)
Requires-Dist: pytest (==6.2.2)
Requires-Dist: requests (==2.25.1)
Requires-Dist: soupsieve (==2.2.1)
Requires-Dist: toml (==0.10.2)
Requires-Dist: urllib3 (==1.26.4)
